LICENSE.txt
README.rst
pyproject.toml
requirements.txt
PyTOA5.egg-info/PKG-INFO
PyTOA5.egg-info/SOURCES.txt
PyTOA5.egg-info/dependency_links.txt
PyTOA5.egg-info/entry_points.txt
PyTOA5.egg-info/requires.txt
PyTOA5.egg-info/top_level.txt
tests/test_toa5.py
toa5/__init__.py
toa5/to_csv/__init__.py
toa5/to_csv/__main__.py