Metadata-Version: 2.1
Name: PyTOA5
Version: 0.9.0
Summary: Utilities for TOA5 Files
Author-email: Hauke D <haukex@zero-g.net>
Project-URL: Documentation, https://haukex.github.io/pytoa5
Project-URL: Repository, https://github.com/haukex/pytoa5
Project-URL: Bug Tracker, https://github.com/haukex/pytoa5/issues
Project-URL: Changelog, https://haukex.github.io/pytoa5#changelog
Classifier: Programming Language :: Python :: 3
Classifier: Programming Language :: Python :: 3.9
Classifier: Programming Language :: Python :: 3.10
Classifier: Programming Language :: Python :: 3.11
Classifier: Programming Language :: Python :: 3.12
Classifier: Programming Language :: Python :: 3.13
Classifier: License :: OSI Approved :: GNU Lesser General Public License v3 or later (LGPLv3+)
Classifier: Development Status :: 5 - Production/Stable
Classifier: Operating System :: POSIX
Classifier: Operating System :: Unix
Classifier: Operating System :: Microsoft :: Windows
Classifier: Operating System :: MacOS :: MacOS X
Classifier: Topic :: File Formats
Classifier: Topic :: Scientific/Engineering
Requires-Python: >=3.9
License-File: LICENSE.txt
Requires-Dist: igbpyutils>=0.8.0
Provides-Extra: test
Requires-Dist: pandas>=2.2.3; extra == "test"
